bst_python_sdk/__init__.py
bst_python_sdk/_swig_parser.cpython-313-darwin.so
bst_python_sdk/bstpacket.py
bst_python_sdk/listener.py
bst_python_sdk/log_to_nc.py
bst_python_sdk/loghandler.py
bst_python_sdk/logparse.py
bst_python_sdk/comm_packets/__init__.py
bst_python_sdk/comm_packets/canpackets.py
bst_python_sdk/comm_packets/comm_packets.py
bst_python_sdk/comm_packets/fixedwing.py
bst_python_sdk/comm_packets/gcs.py
bst_python_sdk/comm_packets/handler.py
bst_python_sdk/comm_packets/multicopter.py
bst_python_sdk/comm_packets/payload.py
bst_python_sdk/comm_packets/tailsitter.py
bst_python_sdk/comm_packets/vtol.py
bst_python_sdk/comm_versions/__init__.py
bst_python_sdk/comm_versions/ver_3160/__init__.py
bst_python_sdk/comm_versions/ver_3160/canpackets.py
bst_python_sdk/comm_versions/ver_3160/comm_packets.py
bst_python_sdk/comm_versions/ver_3160/fixedwing.py
bst_python_sdk/comm_versions/ver_3160/gcs.py
bst_python_sdk/comm_versions/ver_3160/handler.py
bst_python_sdk/comm_versions/ver_3160/multicopter.py
bst_python_sdk/comm_versions/ver_3160/payload.py
bst_python_sdk/comm_versions/ver_3160/tailsitter.py
bst_python_sdk/comm_versions/ver_3160/vtol.py
bst_python_sdk/comm_versions/ver_3170/__init__.py
bst_python_sdk/comm_versions/ver_3170/canpackets.py
bst_python_sdk/comm_versions/ver_3170/comm_packets.py
bst_python_sdk/comm_versions/ver_3170/fixedwing.py
bst_python_sdk/comm_versions/ver_3170/gcs.py
bst_python_sdk/comm_versions/ver_3170/handler.py
bst_python_sdk/comm_versions/ver_3170/multicopter.py
bst_python_sdk/comm_versions/ver_3170/payload.py
bst_python_sdk/comm_versions/ver_3170/tailsitter.py
bst_python_sdk/comm_versions/ver_3170/vtol.py
bst_python_sdk/comm_versions/ver_3190/__init__.py
bst_python_sdk/comm_versions/ver_3190/canpackets.py
bst_python_sdk/comm_versions/ver_3190/comm_packets.py
bst_python_sdk/comm_versions/ver_3190/fixedwing.py
bst_python_sdk/comm_versions/ver_3190/gcs.py
bst_python_sdk/comm_versions/ver_3190/handler.py
bstpythonsdk-3.22.0.dev4.dist-info/licenses/LICENSE
bstpythonsdk-3.22.0.dev4.dist-info/METADATA
bstpythonsdk-3.22.0.dev4.dist-info/WHEEL
bstpythonsdk-3.22.0.dev4.dist-info/top_level.txt
bstpythonsdk-3.22.0.dev4.dist-info/RECORD
