Metadata-Version: 2.4
Name: BSTPythonSDK
Version: 3.22.0.dev4
Summary: BST Flight Management SDK
Home-page: https://github.com/bstaero/sdk
Author: Black Swift Technologies
Author-email: ben.busby@blackswifttech.com
Classifier: Programming Language :: Python :: 3
Classifier: License :: OSI Approved :: GNU General Public License v2 (GPLv2)
Classifier: Operating System :: OS Independent
License-File: LICENSE
Requires-Dist: numpy
Requires-Dist: scipy
Requires-Dist: netCDF4
Dynamic: author
Dynamic: author-email
Dynamic: classifier
Dynamic: description
Dynamic: description-content-type
Dynamic: home-page
Dynamic: license-file
Dynamic: requires-dist
Dynamic: summary
